{
  "id": "020ee3e6-7745-4a66-87ed-8b524ae07b43",
  "prevId": "00000000-0000-0000-0000-000000000000",
  "version": "7",
  "dialect": "postgresql",
  "tables": {
    "public.payments": {
      "name": "payments",
      "schema": "",
      "columns": {
        "id": {
          "name": "id",
          "type": "serial",
          "primaryKey": true,
          "notNull": true
        },
        "phone": {
          "name": "phone",
          "type": "varchar(15)",
          "primaryKey": false,
          "notNull": true
        },
        "amount": {
          "name": "amount",
          "type": "integer",
          "primaryKey": false,
          "notNull": true
        },
        "status": {
          "name": "status",
          "type": "varchar(50)",
          "primaryKey": false,
          "notNull": false,
          "default": "'pending'"
        },
        "transaction_id": {
          "name": "transaction_id",
          "type": "varchar(100)",
          "primaryKey": false,
          "notNull": true
        },
        "merchant_request_id": {
          "name": "merchant_request_id",
          "type": "varchar(100)",
          "primaryKey": false,
          "notNull": true
        },
        "checkout_request_id": {
          "name": "checkout_request_id",
          "type": "varchar(100)",
          "primaryKey": false,
          "notNull": true
        },
        "created_at": {
          "name": "created_at",
          "type": "timestamp",
          "primaryKey": false,
          "notNull": false,
          "default": "now()"
        }
      },
      "indexes": {},
      "foreignKeys": {},
      "compositePrimaryKeys": {},
      "uniqueConstraints": {
        "payments_transaction_id_unique": {
          "name": "payments_transaction_id_unique",
          "nullsNotDistinct": false,
          "columns": [
            "transaction_id"
          ]
        }
      },
      "policies": {},
      "checkConstraints": {},
      "isRLSEnabled": false
    }
  },
  "enums": {},
  "schemas": {},
  "sequences": {},
  "roles": {},
  "policies": {},
  "views": {},
  "_meta": {
    "columns": {},
    "schemas": {},
    "tables": {}
  }
}